descartes/__init__.py
descartes/patch.py
descartes/tests.py
descartes-1.0.2.dist-info/DESCRIPTION.rst
descartes-1.0.2.dist-info/METADATA
descartes-1.0.2.dist-info/metadata.json
descartes-1.0.2.dist-info/RECORD
descartes-1.0.2.dist-info/top_level.txt
descartes-1.0.2.dist-info/WHEEL
