Metadata-Version: 1.1
Name: descartes
Version: 1.0.2
Summary: Use geometric objects as matplotlib paths and patches
Home-page: http://bitbucket.org/sgillies/descartes/
Author: Sean Gillies
Author-email: sean.gillies@gmail.com
License: BSD
Keywords: matplotlib gis geojson geometry
Platform: UNKNOWN
Classifier: Development Status :: 5 - Production/Stable
Classifier: Intended Audience :: Developers
Classifier: Intended Audience :: Science/Research
Classifier: License :: OSI Approved :: BSD License
Classifier: Operating System :: OS Independent
Classifier: Programming Language :: Python
Classifier: Programming Language :: Python :: 2
Classifier: Programming Language :: Python :: 3
Classifier: Topic :: Scientific/Engineering :: GIS
